cdxj_util/__init__.py
cdxj_util/async_core.py
cdxj_util/config.py
cdxj_util/core.py
cdxj_util/exceptions.py
cdxj_util/retrieval.py
cdxj_util/search.py
cdxj_util/stats.py
cdxj_util/utils.py
cdxj_util/validation.py
cdxj_util-1.0.0.dist-info/LICENSE
cdxj_util-1.0.0.dist-info/METADATA
cdxj_util-1.0.0.dist-info/WHEEL
cdxj_util-1.0.0.dist-info/top_level.txt
cdxj_util-1.0.0.dist-info/RECORD
