Metadata-Version: 2.1
Name: cdxj-util
Version: 1.0.0
Summary: A utility library for working with CDXJ files
Home-page: https://github.com/r74tech/cdxj-util
Author: r74tech
Author-email: r74tech@gmail.com
Keywords: cdxj openwayback wayback
Classifier: Development Status :: 3 - Alpha
Classifier: Intended Audience :: Developers
Classifier: License :: OSI Approved :: MIT License
Classifier: Operating System :: OS Independent
Classifier: Programming Language :: Python :: 3
Requires-Python: >=3.7
License-File: LICENSE
Requires-Dist: aiofiles
Provides-Extra: dev
Requires-Dist: pytest; extra == "dev"
Requires-Dist: pytest-asyncio; extra == "dev"
